bio2bel_go/__init__.py
bio2bel_go/__main__.py
bio2bel_go/cli.py
bio2bel_go/constants.py
bio2bel_go/dsl.py
bio2bel_go/manager.py
bio2bel_go/models.py
bio2bel_go/parser.py
bio2bel_go-0.0.1.dist-info/AUTHORS.rst
bio2bel_go-0.0.1.dist-info/LICENSE
bio2bel_go-0.0.1.dist-info/METADATA
bio2bel_go-0.0.1.dist-info/WHEEL
bio2bel_go-0.0.1.dist-info/entry_points.txt
bio2bel_go-0.0.1.dist-info/top_level.txt
bio2bel_go-0.0.1.dist-info/RECORD
