Metadata-Version: 2.1
Name: bio2bel-go
Version: 0.0.1
Summary: A package for converting GO to BEL
Home-page: https://github.com/bio2bel/go
Author: Charles Tapley Hoyt
Author-email: charles.hoyt@scai.fraunhofer.de
Maintainer: Charles Tapley Hoyt
Maintainer-email: charles.hoyt@scai.fraunhofer.de
License: MIT License
Keywords: Biological Expression Language,BEL,Systems Biology,Networks Biology,Gene Ontology
Platform: UNKNOWN
Classifier: Development Status :: 4 - Beta
Classifier: Environment :: Console
Classifier: Intended Audience :: Developers
Classifier: Intended Audience :: Science/Research
Classifier: License :: OSI Approved :: MIT License
Classifier: Operating System :: OS Independent
Classifier: Programming Language :: Python
Classifier: Programming Language :: Python :: 3.6
Classifier: Topic :: Scientific/Engineering :: Bio-Informatics
Requires-Dist: networkx (>=2.1)
Requires-Dist: pybel (<0.13.0,>=0.12.0)
Requires-Dist: obonet
Requires-Dist: click
Requires-Dist: bio2bel (>=0.1.3)
Requires-Dist: tqdm
Requires-Dist: sqlalchemy
